QuadQuanta/__init__.py
QuadQuanta/config.py
QuadQuanta/const.py
QuadQuanta/requirements.txt
QuadQuanta/core/__init__.py
QuadQuanta/core/strategy.py
QuadQuanta/data/__init__.py
QuadQuanta/data/clickhouse_api.py
QuadQuanta/data/data_trans.py
QuadQuanta/data/get_data.py
QuadQuanta/data/mongodb_api.py
QuadQuanta/data/save_data.py
QuadQuanta/data/update_data.py
QuadQuanta/data/update_test.py
QuadQuanta/portfolio/__init__.py
QuadQuanta/portfolio/account.py
QuadQuanta/portfolio/position.py
QuadQuanta/tests/__init__.py
QuadQuanta/tests/test_data/__init__.py
QuadQuanta/tests/test_data/test_clickhouse_api.py
QuadQuanta/tests/test_utils/__init__.py
QuadQuanta/tests/test_utils/test_common.py
QuadQuanta/tests/test_utils/test_datetime_func.py
QuadQuanta/utils/__init__.py
QuadQuanta/utils/common.py
QuadQuanta/utils/datetime_func.py
QuadQuanta/utils/logs.py
QuadQuanta-0.5.2.dist-info/LICENSE
QuadQuanta-0.5.2.dist-info/METADATA
QuadQuanta-0.5.2.dist-info/WHEEL
QuadQuanta-0.5.2.dist-info/top_level.txt
QuadQuanta-0.5.2.dist-info/RECORD
