Metadata-Version: 2.1
Name: QuadQuanta
Version: 0.5.2
Summary: To build a quantification system
Home-page: https://github.com/Naza3/QuadQuanta
Author: Naza3
Author-email: UNKNOWN
License: MIT license
Platform: UNKNOWN
Classifier: Programming Language :: Python
Classifier: Operating System :: Microsoft :: Windows
Classifier: Operating System :: Unix
Classifier: Programming Language :: Python :: 3.4
Classifier: Programming Language :: Python :: 3.5
Classifier: Programming Language :: Python :: 3.6
Classifier: Programming Language :: Python :: 3.7
Classifier: Programming Language :: Python :: 3.8
Requires-Dist: clickhouse-connect==0.7.18
Requires-Dist: jqdatasdk==1.8.10
Requires-Dist: loguru==0.6.0
Requires-Dist: numpy==1.22.3
Requires-Dist: pandas==1.4.0
Requires-Dist: pymongo==3.12.1
Requires-Dist: python-dateutil==2.8.2
Requires-Dist: PyYAML==6.0
Requires-Dist: tqdm==4.64.0
